grascii/__init__.py
grascii/__main__.py
grascii/config.py
grascii/defaults.conf
grascii/defaults.py
grascii/dephrase.py
grascii/grammar.py
grascii/interactive.py
grascii/interpreter.py
grascii/lark_ambig_tools.py
grascii/metrics.py
grascii/outline.py
grascii/parser.py
grascii/regen.py
grascii/search.py
grascii/searchers.py
grascii/similarities.py
grascii/validator.py
grascii/dictionary/__init__.py
grascii/dictionary/__main__.py
grascii/dictionary/build.py
grascii/dictionary/common.py
grascii/dictionary/install.py
grascii/dictionary/list.py
grascii/dictionary/pipeline.py
grascii/dictionary/uninstall.py
grascii/dictionary/preanniversary/A
grascii/dictionary/preanniversary/B
grascii/dictionary/preanniversary/C
grascii/dictionary/preanniversary/D
grascii/dictionary/preanniversary/E
grascii/dictionary/preanniversary/F
grascii/dictionary/preanniversary/G
grascii/dictionary/preanniversary/I
grascii/dictionary/preanniversary/J
grascii/dictionary/preanniversary/K
grascii/dictionary/preanniversary/L
grascii/dictionary/preanniversary/M
grascii/dictionary/preanniversary/N
grascii/dictionary/preanniversary/O
grascii/dictionary/preanniversary/P
grascii/dictionary/preanniversary/R
grascii/dictionary/preanniversary/S
grascii/dictionary/preanniversary/T
grascii/dictionary/preanniversary/U
grascii/dictionary/preanniversary/V
grascii/dictionary/preanniversary/Z
grascii/dictionary/preanniversary-phrases/A
grascii/dictionary/preanniversary-phrases/B
grascii/dictionary/preanniversary-phrases/C
grascii/dictionary/preanniversary-phrases/D
grascii/dictionary/preanniversary-phrases/E
grascii/dictionary/preanniversary-phrases/F
grascii/dictionary/preanniversary-phrases/G
grascii/dictionary/preanniversary-phrases/I
grascii/dictionary/preanniversary-phrases/J
grascii/dictionary/preanniversary-phrases/K
grascii/dictionary/preanniversary-phrases/L
grascii/dictionary/preanniversary-phrases/M
grascii/dictionary/preanniversary-phrases/N
grascii/dictionary/preanniversary-phrases/O
grascii-0.7.0.dist-info/licenses/LICENSE
grascii-0.7.0.dist-info/METADATA
grascii-0.7.0.dist-info/WHEEL
grascii-0.7.0.dist-info/entry_points.txt
grascii-0.7.0.dist-info/top_level.txt
grascii-0.7.0.dist-info/RECORD
