Metadata-Version: 2.4
Name: grascii
Version: 0.7.0
Summary: A language with tools to facilitate the study of Gregg Shorthand.
Home-page: https://github.com/grascii/grascii
Author: Chanic Panic
Author-email: dev@chanicpanic.com
License: MIT
Keywords: shorthand,gregg shorthand,dictionary
Platform: any
Classifier: Development Status :: 3 - Alpha
Classifier: Environment :: Console
Classifier: Intended Audience :: Developers
Classifier: Intended Audience :: End Users/Desktop
Classifier: License :: OSI Approved :: MIT License
Classifier: Natural Language :: English
Classifier: Operating System :: OS Independent
Classifier: Programming Language :: Python :: 3
Classifier: Programming Language :: Python :: 3 :: Only
Classifier: Programming Language :: Python :: 3.9
Classifier: Programming Language :: Python :: 3.10
Classifier: Programming Language :: Python :: 3.11
Classifier: Programming Language :: Python :: 3.12
Classifier: Programming Language :: Python :: 3.13
Classifier: Programming Language :: Python :: Implementation :: CPython
Classifier: Topic :: Text Processing :: General
Classifier: Topic :: Text Processing :: Linguistic
Requires-Python: >=3.9
License-File: LICENSE
Requires-Dist: lark==1.*,>=1.1.8
Requires-Dist: platformdirs~=4.0
Provides-Extra: interactive
Requires-Dist: questionary>=1.5.1; extra == "interactive"
Provides-Extra: docs
Requires-Dist: Sphinx==7.4.7; extra == "docs"
Requires-Dist: sphinx-rtd-theme==3.0.2; extra == "docs"
Requires-Dist: sphinxcontrib-apidoc==0.6.0; extra == "docs"
Requires-Dist: myst-parser==3.0.1; extra == "docs"
Provides-Extra: tests
Requires-Dist: pexpect~=4.0; platform_system != "Windows" and extra == "tests"
Requires-Dist: pytest~=8.4; extra == "tests"
Requires-Dist: pytest-cov~=6.0; extra == "tests"
Requires-Dist: pytest-subtests~=0.7; extra == "tests"
Dynamic: license-file
